confenv/__init__.py
confenv/django.py
django_confenv-1.1.4.dist-info/DESCRIPTION.rst
django_confenv-1.1.4.dist-info/METADATA
django_confenv-1.1.4.dist-info/RECORD
django_confenv-1.1.4.dist-info/WHEEL
django_confenv-1.1.4.dist-info/metadata.json
django_confenv-1.1.4.dist-info/top_level.txt
